deflacue/__init__.py
deflacue/cli.py
deflacue/deflacue.py
deflacue/exceptions.py
deflacue/parser.py
deflacue-2.0.1.dist-info/AUTHORS
deflacue-2.0.1.dist-info/LICENSE
deflacue-2.0.1.dist-info/METADATA
deflacue-2.0.1.dist-info/WHEEL
deflacue-2.0.1.dist-info/entry_points.txt
deflacue-2.0.1.dist-info/top_level.txt
deflacue-2.0.1.dist-info/RECORD
